Workbook

Sheet SU_Budget_FRG-A410-06-02
B1: ACADEMIC ACTIVITIES GRANT BUDGET FORM
B2: OFFICE OF RESEARCH AND GRADUATE POLICY
A3: PROJECT PI:
A4: PROJECT TITLE:
A5: PLEASE INDICATE BUDGET CURRENCY: | E5: TL
A7: COSTS
A8: SCHOLARSHIPS | C8: Unit Cost | D8: Time (hours) | F8: Proposed Budget
A9: Graduate MS / MA | F9: =C9*D9 -> 0
A10: Post-doc | F10: =C10*D10 -> 0
A11: Graduate PhD Stipend | F11: =C11*D11 -> 0
A12: Workstudy | F12: =C12*D12 -> 0
A13: SCHOLARSHIPS BUDGET | F13: =SUM(F9:F12) -> 0
A14: TRAVEL & ACCOMODATION | C14: Unit Cost | D14: # of trips or days | E14: Number of Person | F14: Proposed Budget
A15: Travel (Domestic) | F15: =C15*D15*E15 -> 0
A16: Travel (Domestic)* | F16: =C16*D16*E16 -> 0
A17: Travel (International) | F17: =C17*D17*E17 -> 0
A18: Travel (Domestic)* | F18: =C18*D18*E18 -> 0
A19: Accomodation for invited speakers | F19: =C19*D19*E19 -> 0
A20: TRAVEL & ACCOMODATION BUDGET | F20: =SUM(F15:F19) -> 0
A21: TRANSPORTATON | C21: Unit Cost | D21: # of trips or days | E21: Number of Person | F21: Proposed Budget
A22: Kadıkoy-campus (return) | F22: =C22*D22*E22 -> 0
A23: Taksim - campus (return) | F23: =C23*D23*E23 -> 0
A24: Kadıkoy-campus (one-way) | F24: =C24*D24*E24 -> 0
A25: Taksim-campus (one-way) | F25: =C25*D25*E25 -> 0
A26: Other | F26: =C26*D26*E26 -> 0
A27: Kampus-airport transfer | F27: =C27*D27*E27 -> 0
A28: TRANSPORTATON BUDGET | F28: =SUM(F22:F27) -> 0
A29: CONSULTANCY | C29: Unit Cost | D29: Number of Person | F29: Proposed Budget
A30: Consultancy for invited speaker1 | F30: =C30*D30 -> 0
A31: Consultancy for invited speaker2** | F31: =C31*D31 -> 0
A32: Consultancy for invited speaker3** | F32: =C32*D32 -> 0
A33: RENTAL | C33: Unit Cost | D33: # of Days | F33: Proposed Budget
A34: Conference place rentals | F34: =C34*D34 -> 0
A35: CONSULTANCY & RENTAL BUDGET | F35: =SUM(F30+F31+F32+F34) -> 0
A36: CONSUMABLE | C36: Unit Cost | D36: Quantity | F36: Proposed Budget
A37: Photocopies & Stationary | F37: =C37*D37 -> 0
A38: Printed material (catalog, brochure etc.) | F38: =C38*D38 -> 0
A39: Promotional Videos, Banners, Photography, CD etc. | F39: =C39*D39 -> 0
A40: Other *** | F40: =C40*D40 -> 0
A41: CONSUMABLE BUDGET | F41: =SUM(F37:F40) -> 0
A42: SERVICE PURCHASES | C42: Amount | F42: Proposed Budget
A43: Translation Services*** | F43: =C43 -> 0
A44: Other Services*** | F44: =C44 -> 0
A45: SERVICE PURCHASES BUDGET | F45: =SUM(F43:F44) -> 0
A46: FOOD & BEVERAGE | C46: Unit Cost | D46: Quantity | F46: Proposed Budget
A47: Cofee Breaks | F47: =C47*D47 -> 0
A48: SU Cafeteria Meals | F48: =C48*D48 -> 0
A49: On-campus Event (cocktail, dinner etc.) | F49: =C49*D49 -> 0
A50: Off-campus Event | F50: =C50*D50 -> 0
A51: Off- campus meeting package | F51: =C51*D51 -> 0
A52: Other Event**** | F52: =C52*D52 -> 0
A53: FOOD & BEVERAGE BUDGET | F53: =SUM(F47:F52) -> 0
A54: TOTAL PROJECT COSTS | F54: =F13+F20+F28+F35+F41+F45+F53 -> 0
A57: Notes
A58: * If different amounts for travel expenses.
A59: ** If different amounts for invited speaker consultancy.
A60: *** This item is not supported outside of international organizations.If you need these items, please explain in detail the application form.
A61: **** If you need these items, please explain in detail the application form.
A63: FRG-A410-06-02

Sheet Total_Budget_FRG-A410-06-02
B1: ACADEMIC ACTIVITIES GRANT BUDGET FORM
B2: OFFICE OF RESEARCH AND GRADUATE POLICY
A3: PROJECT PI:
A4: PROJECT TITLE:
A5: PLEASE INDICATE BUDGET CURRENCY: | E5: TL
A7: COSTS
A8: SCHOLARSHIPS | C8: SU Proposed Budget | D8: External Budget | E8: Total Budget
A9: Graduate MS / MA | C9: ='SU_Budget_FRG-A410-06-02'!F9 -> 0 | E9: =C9+D9 -> 0
A10: Post-doc | C10: ='SU_Budget_FRG-A410-06-02'!F10 -> 0 | E10: =C10+D10 -> 0
A11: Graduate PhD Stipend | C11: ='SU_Budget_FRG-A410-06-02'!F11 -> 0 | E11: =C11+D11 -> 0
A12: Workstudy | C12: ='SU_Budget_FRG-A410-06-02'!F12 -> 0 | E12: =C12+D12 -> 0
A13: SCHOLARSHIPS BUDGET | C13: =SUM(C9:C12) -> 0 | D13: =SUM(D9:D12) -> 0 | E13: =SUM(E9:E12) -> 0
A14: TRAVEL & ACCOMODATION | C14: SU Proposed Budget | D14: External Budget | E14: Total Budget
A15: Travel (Domestic) | C15: ='SU_Budget_FRG-A410-06-02'!F15 -> 0 | E15: =C15+D15 -> 0
A16: Travel (Domestic)* | C16: ='SU_Budget_FRG-A410-06-02'!F16 -> 0 | E16: =C16+D16 -> 0
A17: Travel (International) | C17: ='SU_Budget_FRG-A410-06-02'!F17 -> 0 | E17: =C17+D17 -> 0
A18: Travel (Domestic)* | C18: ='SU_Budget_FRG-A410-06-02'!F18 -> 0 | E18: =C18+D18 -> 0
A19: Accomodation for invited speakers | C19: ='SU_Budget_FRG-A410-06-02'!F19 -> 0 | E19: =C19+D19 -> 0
A20: TRAVEL & ACCOMODATION BUDGET | C20: =SUM(C15:C19) -> 0 | D20: =SUM(D15:D19) -> 0 | E20: =SUM(E15:E19) -> 0
A21: TRANSPORTATON | C21: SU Proposed Budget | D21: External Budget | E21: Total Budget
A22: Kadıkoy-campus (return) | C22: ='SU_Budget_FRG-A410-06-02'!F22 -> 0 | E22: =C22+D22 -> 0
A23: Taksim - campus (return) | C23: ='SU_Budget_FRG-A410-06-02'!F23 -> 0 | E23: =C23+D23 -> 0
A24: Kadıkoy-campus (one-way) | C24: ='SU_Budget_FRG-A410-06-02'!F24 -> 0 | E24: =C24+D24 -> 0
A25: Taksim-campus (one-way) | C25: ='SU_Budget_FRG-A410-06-02'!F25 -> 0 | E25: =C25+D25 -> 0
A26: Other | C26: ='SU_Budget_FRG-A410-06-02'!F26 -> 0 | E26: =C26+D26 -> 0
A27: Kampus-airport transfer | C27: ='SU_Budget_FRG-A410-06-02'!F27 -> 0 | E27: =C27+D27 -> 0
A28: TRANSPORTATON BUDGET | C28: =SUM(C22:C27) -> 0 | D28: =SUM(D22:D27) -> 0 | E28: =SUM(E22:E27) -> 0
A29: CONSULTANCY | C29: SU Proposed Budget | D29: External Budget | E29: Total Budget
A30: Consultancy for invited speaker1 | C30: ='SU_Budget_FRG-A410-06-02'!F30 -> 0 | E30: =C30+D30 -> 0
A31: Consultancy for invited speaker2* | C31: ='SU_Budget_FRG-A410-06-02'!F31 -> 0 | E31: =C31+D31 -> 0
A32: Consultancy for invited speaker3* | C32: ='SU_Budget_FRG-A410-06-02'!F32 -> 0 | E32: =C32+D32 -> 0
A33: RENTAL | C33: SU Proposed Budget | D33: External Budget | E33: Total Budget
A34: Conference place rentals | C34: ='SU_Budget_FRG-A410-06-02'!F34 -> 0 | E34: =C34+D34 -> 0
A35: CONSULTANCY & RENTAL BUDGET | C35: =SUM(C30+C31+C32+C34) -> 0 | D35: =SUM(D30+D31+D32+D34) -> 0 | E35: =SUM(E30+E31+E32+E34) -> 0
A36: CONSUMABLE | C36: SU Proposed Budget | D36: External Budget | E36: Total Budget
A37: Photocopies & Stationary | C37: ='SU_Budget_FRG-A410-06-02'!F37 -> 0 | E37: =C37+D37 -> 0
A38: Printed material (catalog, brochure etc.) | C38: ='SU_Budget_FRG-A410-06-02'!F38 -> 0 | E38: =C38+D38 -> 0
A39: Promotional Videos, Banners, Photography, CD etc. | C39: ='SU_Budget_FRG-A410-06-02'!F39 -> 0 | E39: =C39+D39 -> 0
A40: Other *** | C40: ='SU_Budget_FRG-A410-06-02'!F40 -> 0 | E40: =C40+D40 -> 0
A41: CONSUMABLE BUDGET | C41: =SUM(C37:C40) -> 0 | D41: =SUM(D37:D40) -> 0 | E41: =SUM(E37:E40) -> 0
A42: SERVICE PURCHASES | C42: SU Proposed Budget | D42: External Budget | E42: Proposed Budget
A43: Translation Services** | C43: ='SU_Budget_FRG-A410-06-02'!F43 -> 0 | E43: =C43+D43 -> 0
A44: Other Services** | C44: ='SU_Budget_FRG-A410-06-02'!F44 -> 0 | E44: =C44+D44 -> 0
A45: SERVICE PURCHASES BUDGET | C45: =SUM(C43:C44) -> 0 | D45: =SUM(D43:D44) -> 0 | E45: =SUM(E43:E44) -> 0
A46: FOOD & BEVERAGE | C46: SU Proposed Budget | D46: External Budget | E46: Total Budget
A47: Cofee Breaks | C47: ='SU_Budget_FRG-A410-06-02'!F47 -> 0 | E47: =C47+D47 -> 0
A48: SU Cafeteria Meals | C48: ='SU_Budget_FRG-A410-06-02'!F48 -> 0 | E48: =C48+D48 -> 0
A49: On-campus Event (cocktail, dinner etc.) | C49: ='SU_Budget_FRG-A410-06-02'!F49 -> 0 | E49: =C49+D49 -> 0
A50: Off-campus Event | C50: ='SU_Budget_FRG-A410-06-02'!F50 -> 0 | E50: =C50+D50 -> 0
A51: Off- campus meeting package | C51: ='SU_Budget_FRG-A410-06-02'!F51 -> 0 | E51: =C51+D51 -> 0
A52: Other Event*** | C52: ='SU_Budget_FRG-A410-06-02'!F52 -> 0 | E52: =C52+D52 -> 0
A53: FOOD & BEVERAGE BUDGET | C53: =SUM(C47:C52) -> 0 | D53: =SUM(D47:D52) -> 0 | E53: =SUM(E47:E52) -> 0
A54: TOTAL PROJECT COSTS | C54: =C13+C20+C28+C35+C41+C45+C53 -> 0 | D54: =D13+D20+D28+D35+D41+D45+D53 -> 0 | E54: =E13+E20+E28+E35+E41+E45+E53 -> 0
A57: Notes
A58: * If different amounts for invited speaker consultancy or travel expenses.
A59: ** This item is not supported outside of international organizations.If you need these items, please explain in detail the application form.
A60: ***If you need these items, please explain in detail the application form.
A62: FRG-A410-06-02
